auto_fast_docs/__init__.py
auto_fast_docs/auto_doc.py
auto_fast_docs/discover.py
auto_fast_docs/mkdocs_template.yml
auto_fast_docs-2.0.6.dist-info/METADATA
auto_fast_docs-2.0.6.dist-info/WHEEL
auto_fast_docs-2.0.6.dist-info/entry_points.txt
auto_fast_docs-2.0.6.dist-info/top_level.txt
auto_fast_docs-2.0.6.dist-info/RECORD
