Metadata-Version: 2.1
Name: auto_fast_docs
Version: 2.0.6
Summary: Automatic code documentation generation tool (to generate markdown files compatible with mkdocstrings)
Author-email: Timothé Jost-Mousseau <timothe.jost-mousseau@pasteur.fr>
Maintainer-email: Timothé Jost-Mousseau <timothe.jost-mousseau@pasteur.fr>
License: MIT
Project-URL: homepage, https://pypi.org/project/auto-fast-docs/
Project-URL: repository, https://github.com/JostTim/auto-doc/
Project-URL: documentation, https://josttim.github.io/auto_fast_docs/
Requires-Python: >=3.10
Requires-Dist: setuptools >=66.0
Requires-Dist: natsort
Requires-Dist: mkdocs
Requires-Dist: mkdocs-material
Requires-Dist: mkdocstrings
Requires-Dist: mkdocstrings-python
